flask_crud/__init__.py
flask_crud/dbutil.py
flask_crud/manage.py
flask_crud/routeutil.py
flask_crud/util.py
flask_crud/view.py
flask_crud/examples/report.py
flask_crud/examples/run.py
flask_crud/examples/app/__init__.py
flask_crud/examples/app/admin_dbmapper.py
flask_crud/examples/app/admin_viewmodel.py
flask_crud/examples/app/dbmappers.py
flask_crud/examples/app/main.py
flask_crud/examples/app/viewmodels.py
flask_crud/examples/app/__pycache__/__init__.cpython-310.pyc
flask_crud/examples/app/__pycache__/admin_dbmapper.cpython-310.pyc
flask_crud/examples/app/__pycache__/admin_viewmodel.cpython-310.pyc
flask_crud/examples/app/__pycache__/config.cpython-310.pyc
flask_crud/examples/app/__pycache__/dbmappers.cpython-310.pyc
flask_crud/examples/app/__pycache__/dbutil.cpython-310.pyc
flask_crud/examples/app/__pycache__/main.cpython-310.pyc
flask_crud/examples/app/__pycache__/models.cpython-310.pyc
flask_crud/examples/app/__pycache__/viewmodels.cpython-310.pyc
flask_crud/examples/app/config/authconfig.py
flask_crud/examples/app/config/dbconfig.py
flask_crud/examples/app/config/permission.py
flask_crud/examples/app/config/viewmodelconfig.py
flask_crud/examples/app/config/__pycache__/authconfig.cpython-310.pyc
flask_crud/examples/app/config/__pycache__/dbconfig.cpython-310.pyc
flask_crud/examples/app/config/__pycache__/permission.cpython-310.pyc
flask_crud/examples/app/config/__pycache__/viewmodelconfig.cpython-310.pyc
flask_crud/examples/app/routes/__init__.py
flask_crud/examples/app/routes/admin.py
flask_crud/examples/app/routes/auth.py
flask_crud/examples/app/routes/base.py
flask_crud/examples/app/routes/db.py
flask_crud/examples/app/routes/index.py
flask_crud/examples/app/routes/options.py
flask_crud/examples/app/routes/__pycache__/__init__.cpython-310.pyc
flask_crud/examples/app/routes/__pycache__/admin.cpython-310.pyc
flask_crud/examples/app/routes/__pycache__/auth.cpython-310.pyc
flask_crud/examples/app/routes/__pycache__/base.cpython-310.pyc
flaski-0.0.0.9.dist-info/LICENSE
flaski-0.0.0.9.dist-info/METADATA
flaski-0.0.0.9.dist-info/WHEEL
flaski-0.0.0.9.dist-info/top_level.txt
flaski-0.0.0.9.dist-info/RECORD
