Metadata-Version: 2.1
Name: flaski
Version: 0.0.0.9
Summary: Administra vistas con un enfoque diferente en flask.
Home-page: https://github.com/jrodre/flask_crud.git
Author: Jodriz Dev
Author-email: jrodriguez7603@utm.edu.ec
License-File: LICENSE
Requires-Dist: Flask
Requires-Dist: Flask-MySQLdb
Requires-Dist: flask-login
Requires-Dist: flask-mysqldb
Requires-Dist: numpy==2.0.1
Requires-Dist: pandas==2.2.2
Requires-Dist: python-dateutil==2.9.0.post0
Requires-Dist: pytz==2024.1
Requires-Dist: six==1.16.0
Requires-Dist: tzdata==2024.1
Requires-Dist: visitor==0.1.3
Requires-Dist: Werkzeug==3.0.3
Requires-Dist: XlsxWriter==3.2.0
Requires-Dist: zipp==3.19.2
